{
  "basketId": "e6660de8-8ca2-451b-af81-a2b5857e2f70",
  "affiliateId": "11",
  "source": "WCS",
  "customerRequestedDate": "2017-10-01T09:45:00.000+02:00",
  "metadata": {
    "returnURL": null,
    "basketStatus": "INCOMPLETE",
    "salesOrderId": null,
    "reason": null
  },
  "journey": {
    "journeyType": "Upgrade",
    "offerCode": null
  },
  "packages": [
    {
      "packageId": "87ec910f-c58a-4948-83f4-9dbe4fb7593b",
      "accountCategory": "Consumer",
      "sequence": 1,
      "packageType": "Upgrade",
      "removable": true,
      "dependentOn": [],
      "voucherCode": null,
      "bundle": {
        "packageLineId": "82cb9d24-57c1-4569-a45e-5b188ecb5dd8",
        "action": "ADD",
        "skuId": "112855",
        "name": "24mth OneNumber for Watch",
        "description": "Bingo OneNumber for Watch 24mth",
        "displayName": "24mth OneNumber for Watch",
        "displayDescription": null,
        "bundleClass": "WATCH",
        "productClass": null,
        "serviceId": "110286",
        "paymentType": "Postpaid",
        "bundleType": null,
        "commitmentPeriod": {
          "uom": "Months",
          "value": "24"
        },
        "displayOrder": null,
        "showInSummary": false,
        "allowances": [],
        "merchandisingMedia": [],
        "attributes": null,
        "benefits": [],
        "priceDetails": {
          "monthlyPrice": {
            "gross": "5",
            "net": "4.17",
            "vat": "0.83"
          },
          "monthlyDiscountPrice": {
            "gross": "5",
            "net": "4.17",
            "vat": "0.83"
          },
          "totalMonthlySavingsAmount": null,
          "merchandisingPromotions": null,
          "listOfMerchandisingPromotion": [],
          "removedPromotionFootNote": null
        },
        "isVodafoneGlobalRoaming": false,
        "bundledServiceProducts": null,
        "planCategory": "CONSUMER",
        "portability": null,
        "speed": null,
        "maxCapSpeed": null,
        "avgDownloadSpeed": null,
        "includedCalls": null,
        "noPriceRise": null,
        "isChanged": false
      },
      "hardwares": [
        {
          "packageLineId": "8fdb751c-024b-4db3-9309-0c243afb785f",
          "action": "ADD",
          "skuId": "202238",
          "name": "Bingo Dummy Watch 2",
          "description": "Galaxy Watch3 lets you live your life to the full and look great while you do it, with its brilliant tech and classic design.",
          "displayName": "Samsung Galaxy Watch3 45mm 4G Mystic Silver",
          "displayDescription": null,
          "deviceBriefDescription": null,
          "deviceColor": null,
          "memorySize": null,
          "make": "samsung",
          "model": "galaxy-watch3-45mm",
          "groupType": null,
          "productClass": "eHandset",
          "productSubClass": "WATCH",
          "displayOrder": null,
          "showInSummary": false,
          "merchandisingMedia": [
            {
              "id": "imageURLs.thumbs.front",
              "value": "/images/desktop/Samsung_Galaxy_Watch_3_45mm_mystic_silver-thumbs-right.png",
              "type": "URL",
              "footNotes": []
            },
            {
              "id": "imageURLs.thumbs.left",
              "value": "/images/desktop/Samsung_Galaxy_Watch_3_45mm_mystic_silver-thumbs-side.png",
              "type": "URL",
              "footNotes": []
            },
            {
              "id": "imageURLs.thumbs.right",
              "value": "/images/desktop/Samsung_Galaxy_Watch_3_45mm_mystic_silver-thumbs-back.png",
              "type": "URL",
              "footNotes": []
            },
            {
              "id": "imageURLs.thumbs.frontAngle",
              "value": "/images/desktop/Samsung_Galaxy_Watch_3_45mm_mystic_silver-full-product-front-600.png",
              "type": "URL",
              "footNotes": []
            },
            {
              "id": "imageURLs.thumbs.backAngle",
              "value": "/images/desktop/Samsung_Galaxy_Watch_3_45mm_mystic_silver-full-product-front-600.png",
              "type": "URL",
              "footNotes": []
            },
            {
              "id": "imageURLs.full.hero",
              "value": "/images/desktop/Samsung_Galaxy_Watch_3_45mm_mystic_silver-full-product-left-600.png",
              "type": "URL",
              "footNotes": []
            },
            {
              "id": "imageURLs.full.front",
              "value": "/images/desktop/Samsung_Galaxy_Watch_3_45mm_mystic_silver-full-product-right-600.png",
              "type": "URL",
              "footNotes": []
            },
            {
              "id": "imageURLs.full.left",
              "value": "/images/desktop/Samsung_Galaxy_Watch_3_45mm_mystic_silver-full-product-side-600.png",
              "type": "URL",
              "footNotes": []
            },
            {
              "id": "imageURLs.full.right",
              "value": "/images/desktop/Samsung_Galaxy_Watch_3_45mm_mystic_silver-full-product-back-600.png",
              "type": "URL",
              "footNotes": []
            },
            {
              "id": "imageURLs.full.frontAngle",
              "value": "/images/desktop/Samsung_Galaxy_Watch_3_45mm_mystic_silver-grid-product-front.png",
              "type": "URL",
              "footNotes": []
            }
          ],
          "attributes": null,
          "contractOptions": {
            "duration": {
              "uom": "MONTH",
              "value": "3"
            },
            "upFrontPrice": 30,
            "customerType": "Consumer"
          },
          "priceDetails": {
            "oneOffPrice": {
              "gross": "40",
              "net": "33.33",
              "vat": "6.67"
            },
            "oneOffDiscountPrice": {
              "gross": "40",
              "net": "33.33",
              "vat": "6.67"
            },
            "merchandisingPromotions": null,
            "monthlyPrice": {
              "gross": null,
              "net": null,
              "vat": null
            },
            "monthlyDiscountPrice": {
              "gross": null,
              "net": null,
              "vat": null
            },
            "financingOptions": null,
            "deviceFinancingId": null,
            "devicePaymentPlan": {
              "aprRepresentative": "0.0",
              "duration": {
                "uom": "MONTH",
                "value": "3"
              },
              "interestRate": "0.0",
              "description": "On a 3-month phone credit agreement",
              "monthlyPrice": {
                "uom": "£",
                "gross": "3.33",
                "net": "2.78",
                "vat": "0.55"
              },
              "totalHandsetCredit": {
                "uom": "£",
                "gross": "10.00",
                "net": "8.33",
                "vat": "1.67"
              },
              "totalHandsetPrice": {
                "uom": "£",
                "gross": "40.00",
                "net": "33.33",
                "vat": "6.67"
              },
              "upFrontPrice": {
                "uom": "£",
                "gross": "30.00",
                "net": "25.00",
                "vat": "5.00"
              }
            }
          },
          "boxPrice": {
            "gross": "3598.80",
            "net": "2999.0",
            "vat": "599.80"
          },
          "freeGift": false,
          "devicePromotion": "112863",
          "simType": "ESIMONLY",
          "isChanged": false,
          "isCompatibleWithWatch": false
        }
      ],
      "services": [
        {
          "packageLineId": "df9f2b64-0a38-483e-a7c5-7a6a82855a58",
          "action": "ADD",
          "skuId": "110177",
          "name": "Fee for Flexi-Upgrade",
          "description": null,
          "displayName": "Fee for Flexi-Upgrade",
          "displayDescription": null,
          "specificationGroup": [],
          "merchandisingMedia": [],
          "attributes": [],
          "priceDetails": {
            "oneOffPrice": {
              "gross": "100.00",
              "net": "83.33",
              "vat": "16.67"
            },
            "oneOffDiscountPrice": {
              "gross": "100.00",
              "net": "83.33",
              "vat": "16.67"
            },
            "monthlyPrice": null,
            "monthlyDiscountPrice": null,
            "merchandisingPromotions": null
          },
          "freeGift": false,
          "productClass": "Fee",
          "dataRollover": null,
          "rootProductId": "110286",
          "allowances": [],
          "rewardPoints": null,
          "planDuration": null,
          "isChanged": false
        }
      ],
      "discounts": [],
      "priceDetails": {
        "oneOffPrice": {
          "gross": "30",
          "net": "25",
          "vat": "5"
        },
        "oneOffDiscountPrice": {
          "gross": "30",
          "net": "25",
          "vat": "5"
        },
        "monthlyPrice": {
          "gross": "8.33",
          "net": "6.95",
          "vat": "1.38"
        },
        "monthlyDiscountPrice": {
          "gross": "8.33",
          "net": "6.95",
          "vat": "1.38"
        },
        "financingOptions": null
      },
      "installationAddress": null,
      "appointmentWindow": null,
      "servicePoint": null,
      "serviceStartDate": null,
      "phoneNumber": null,
      "primaryDeviceIdentifier": "+447000000013",
      "packageLinkIdentifier": null,
      "linePackageType": null,
      "lineTreatmentType": null,
      "planType": "BINGO",
      "combiPackageId": null,
      "confirmRequired": false,
      "deviceFinancingId": null,
      "additionalDetails": null,
      "isChanged": false
    }
  ],
  "vetOutcome": null,
  "priceDetails": {
    "oneOffPrice": {
      "gross": "30",
      "net": "25",
      "vat": "5"
    },
    "oneOffDiscountPrice": {
      "gross": "30",
      "net": "25",
      "vat": "5"
    },
    "monthlyPrice": {
      "gross": "8.33",
      "net": "6.95",
      "vat": "1.38"
    },
    "monthlyDiscountPrice": {
      "gross": "8.33",
      "net": "6.95",
      "vat": "1.38"
    },
    "totalOneoffSaving": {
      "gross": "0",
      "net": "0",
      "vat": "0"
    },
    "totalMonthlySaving": {
      "gross": "0",
      "net": "0",
      "vat": "0"
    }
  },
  "totalOneoffPriceSaving": "0",
  "totalMonthlyPriceSaving": "0",
  "deliveryInfo": null,
  "voucherCode": null,
  "voucherDescription": null,
  "validated": true,
  "hashvalue": "-1050671859",
  "lastModified": null,
  "changeCode": null,
  "combiPackageIds": [],
  "voucherErrorMessage": null,
  "activeBundles": [
    {
      "packageLineId": "1a9d99ef-dcfc-4eb0-b646-a1ec99007fee",
      "bundleId": "110082",
      "identifier": {
        "key": "msisdn",
        "value": "447000000020"
      },
      "assetIntegrationId": "1-73ASQ30",
      "activeDiscounts": [
        {
          "discountId": "111116",
          "offerId": null,
          "qualifier": null
        },
        {
          "discountId": "107427",
          "offerId": null,
          "qualifier": null
        }
      ],
      "bundlePrice": {
        "bundleId": "110082",
        "monthlyPrice": {
          "gross": "51.79",
          "net": "43.16",
          "vat": "8.63"
        },
        "monthlyDiscountPrice": {
          "gross": "51.79",
          "net": "43.16",
          "vat": "8.63"
        },
        "merchandisingPromotions": null
      },
      "isActiveSubscription": true
    }
  ],
  "splitDeliveryEligible": false,
  "priceProposal": [],
  "loanEligibilityStatus": null,
  "affiliateFlag": false,
  "isChanged": false
}